jupyter_labelstudio_extension/__init__.py
jupyter_labelstudio_extension/_version.py
jupyter_labelstudio_extension/handlers.py
jupyter_labelstudio_extension/server.py
jupyter_labelstudio_extension/labextension/build_log.json
jupyter_labelstudio_extension/labextension/install.json
jupyter_labelstudio_extension/labextension/package.json
jupyter_labelstudio_extension/labextension/static/lib_index_js.ad154e317e0a4114e232.js
jupyter_labelstudio_extension/labextension/static/lib_index_js.ad154e317e0a4114e232.js.map
jupyter_labelstudio_extension/labextension/static/remoteEntry.28f906c4da48172fb784.js
jupyter_labelstudio_extension/labextension/static/remoteEntry.28f906c4da48172fb784.js.map
jupyter_labelstudio_extension/labextension/static/style.js
jupyter_labelstudio_extension/labextension/static/style_index_js.6a572ecc75a7969991c4.js
jupyter_labelstudio_extension/labextension/static/style_index_js.6a572ecc75a7969991c4.js.map
jupyter_labelstudio_extension/labextension/static/vendors-node_modules_codemirror_autocomplete_dist_index_js.c0a2a2887a44cf1ad7a4.js
jupyter_labelstudio_extension/labextension/static/vendors-node_modules_codemirror_autocomplete_dist_index_js.c0a2a2887a44cf1ad7a4.js.map
jupyter_labelstudio_extension/labextension/static/vendors-node_modules_codemirror_lang-html_dist_index_js.87f3d55bb93d2f789e6d.js
jupyter_labelstudio_extension/labextension/static/vendors-node_modules_codemirror_lang-html_dist_index_js.87f3d55bb93d2f789e6d.js.map
jupyter_labelstudio_extension/labextension/static/vendors-node_modules_css-loader_dist_runtime_api_js-node_modules_css-loader_dist_runtime_cssW-72eba1.520c3917a890de09f6a6.js
jupyter_labelstudio_extension/labextension/static/vendors-node_modules_css-loader_dist_runtime_api_js-node_modules_css-loader_dist_runtime_cssW-72eba1.520c3917a890de09f6a6.js.map
jupyter_labelstudio_extension/labextension/static/vendors-node_modules_label-studio_build_static_css_main_css.20c25e5ae408b969aceb.js
jupyter_labelstudio_extension-0.2.1.dist-info/METADATA
jupyter_labelstudio_extension-0.2.1.dist-info/WHEEL
jupyter_labelstudio_extension-0.2.1.dist-info/licenses/LICENSE
jupyter_labelstudio_extension-0.2.1.dist-info/RECORD
