Metadata-Version: 2.1
Name: jupyter_labelstudio_extension
Version: 0.2.1
Summary: An extension for quick labeling with LabelStudio in jupyterlab
Project-URL: Homepage, https://github.com/MountPOTATO/jupyterlab-label-studio-extension
Project-URL: Bug Tracker, https://github.com/MountPOTATO/jupyterlab-label-studio-extension/issues
Project-URL: Repository, https://github.com/MountPOTATO/jupyterlab-label-studio-extension.git
Author-email: MountPotato <mountpotatoes@gmail.com>
License: BSD 3-Clause License
License-File: LICENSE
Classifier: Framework :: Jupyter
Classifier: Framework :: Jupyter :: JupyterLab
Classifier: Framework :: Jupyter :: JupyterLab :: 3
Classifier: Framework :: Jupyter :: JupyterLab :: Extensions
Classifier: Framework :: Jupyter :: JupyterLab :: Extensions :: Prebuilt
Classifier: License :: OSI Approved :: BSD License
Classifier: Programming Language :: Python
Classifier: Programming Language :: Python :: 3
Classifier: Programming Language :: Python :: 3.7
Classifier: Programming Language :: Python :: 3.8
Classifier: Programming Language :: Python :: 3.9
Classifier: Programming Language :: Python :: 3.10
Requires-Python: >=3.7
Requires-Dist: jupyter-server<2,>=1.6
Requires-Dist: label-studio-sdk>=0.0.15
Requires-Dist: pandas
Provides-Extra: test
Requires-Dist: coverage; extra == 'test'
Requires-Dist: pytest; extra == 'test'
Requires-Dist: pytest-asyncio; extra == 'test'
Requires-Dist: pytest-cov; extra == 'test'
Requires-Dist: pytest-tornasync; extra == 'test'
